cuqipy_fenics/__init__.py
cuqipy_fenics/_version.py
cuqipy_fenics/config.py
cuqipy_fenics/geometry.py
cuqipy_fenics/pde.py
cuqipy_fenics/testproblem.py
cuqipy_fenics/utilities.py
cuqipy_fenics-0.10.0.dist-info/licenses/LICENSE
cuqipy_fenics-0.10.0.dist-info/METADATA
cuqipy_fenics-0.10.0.dist-info/WHEEL
cuqipy_fenics-0.10.0.dist-info/top_level.txt
cuqipy_fenics-0.10.0.dist-info/RECORD
