Metadata-Version: 2.4
Name: CUQIpy-FEniCS
Version: 0.10.0
Summary: CUQIpy plugin for FEniCS
Maintainer-email: "Nicolai A. B. Riis" <nabr@dtu.dk>, "Jakob S. Jørgensen" <jakj@dtu.dk>, "Amal M. Alghamdi" <amaal@dtu.dk>
License:                     GNU GENERAL PUBLIC LICENSE
Project-URL: Source, https://github.com/CUQI-DTU/CUQIpy-FEniCS
Project-URL: Download, https://github.com/CUQI-DTU/CUQIpy-FEniCS/releases
Requires-Python: >=3.8
License-File: LICENSE
Requires-Dist: cuqipy
Dynamic: license-file
